dispanderfixed/__init__.py
dispanderfixed/module.py
newdispanderfixed/__init__.py
newdispanderfixed/module.py
newdispanderfixed-0.1.5.dist-info/LICENSE
newdispanderfixed-0.1.5.dist-info/METADATA
newdispanderfixed-0.1.5.dist-info/WHEEL
newdispanderfixed-0.1.5.dist-info/top_level.txt
newdispanderfixed-0.1.5.dist-info/RECORD
