Metadata-Version: 2.1
Name: newdispanderfixed
Version: 0.1.5
Summary: A fork of Discord Message URL Expander for d.py 2.0.0a/pycord
Home-page: UNKNOWN
Author: susi-chaaaan
Author-email: sushi_code@outlook.jp
License: UNKNOWN
Platform: UNKNOWN
Classifier: Programming Language :: Python :: 3.10
Classifier: Operating System :: OS Independent
License-File: LICENSE
